LICENSE
MANIFEST.in
README
README.md
makefile
mkenv
requirements.txt
setup.cfg
setup.py
test-requirements.txt
bin/kez
kez/__init__.py
kez/exceptions.py
kez/manager.py
kez/models.py
kez.egg-info/PKG-INFO
kez.egg-info/SOURCES.txt
kez.egg-info/dependency_links.txt
kez.egg-info/not-zip-safe
kez.egg-info/top_level.txt
kez/builders/__init__.py
kez/builders/base.py
kez/builders/pelican/__init__.py
kez/builders/pelican/builder.py
kez/builders/pelican/plugins/__init__.py
kez/builders/pelican/plugins/html_rst_directive.py
kez/builders/pelican/plugins/ipython.py
kez/builders/pelican/plugins/multi_part.py
kez/builders/pelican/plugins/neighbors.py
kez/ui/__init__.py
kez/ui/application.py
kez/ui/commands/__init__.py
kez/ui/commands/base.py
kez/utils/__init__.py
kez/utils/base.py
kez/utils/path.py
kez/utils/process.py
kez/utils/sync.py
kez/utils/typedinterpolation.py
tests/__init__.py
tests/conftest.py
tests/test_manager.py
tests/test_models.py
tests/test_pelican.py
tests/test_ui.py
tests/test_utils.py
tests/usage.rst
tests/data/__init__.py
tests/data/example.cfg
tests/data/pelican/samples/advanced/pelican.conf.py
tests/data/pelican/samples/advanced/content/2012-11-30_filename-metadata.rst
tests/data/pelican/samples/advanced/content/another_super_article-fr.rst
tests/data/pelican/samples/advanced/content/another_super_article.rst
tests/data/pelican/samples/advanced/content/article2-fr.rst
tests/data/pelican/samples/advanced/content/article2.rst
tests/data/pelican/samples/advanced/content/article_tag_baz.rst
tests/data/pelican/samples/advanced/content/draft_article.rst
tests/data/pelican/samples/advanced/content/super_article.rst
tests/data/pelican/samples/advanced/content/unbelievable.rst
tests/data/pelican/samples/advanced/content/unwanted_file
tests/data/pelican/samples/advanced/content/cat1/article1.rst
tests/data/pelican/samples/advanced/content/cat1/article2.rst
tests/data/pelican/samples/advanced/content/cat1/article3.rst
tests/data/pelican/samples/advanced/content/cat1/markdown-article.md
tests/data/pelican/samples/advanced/content/extra/robots.txt
