Metadata-Version: 1.1
Name: kez
Version: 0.1.5
Summary: CLI for tracking and building documents, specifically Pelican static blogs
Home-page: https://github.com/averagehuman/kez
Author: gmf
Author-email: gmflanagan@outlook.com
License: BSD
Platform: UNKNOWN
Classifier: Development Status :: 4 - Beta
Classifier: Intended Audience :: Developers
Classifier: License :: OSI Approved :: BSD License
Classifier: Programming Language :: Python
Classifier: Topic :: Software Development :: Libraries
Classifier: Topic :: Software Development :: Libraries :: Python Modules
